design.sv
module full_adder (
    input A, B, Cin,
    output Sum, Cout
);
    assign Sum  = A ^ B ^ Cin;
    assign Cout = (A & B) | (B & Cin) | (A & Cin);
endmodule

module parallel_adder_4bit (
    input  [3:0] A, B,
    input        Cin,
    output [3:0] Sum,
    output       Cout
);

    wire c1, c2, c3;

    full_adder fa0 (.A(A[0]), .B(B[0]), .Cin(Cin),  .Sum(Sum[0]), .Cout(c1));
    full_adder fa1 (.A(A[1]), .B(B[1]), .Cin(c1),   .Sum(Sum[1]), .Cout(c2));
    full_adder fa2 (.A(A[2]), .B(B[2]), .Cin(c2),   .Sum(Sum[2]), .Cout(c3));
    full_adder fa3 (.A(A[3]), .B(B[3]), .Cin(c3),   .Sum(Sum[3]), .Cout(Cout));

endmodule

testbench.sv
module tb_parallel_adder_4bit;

    reg [3:0] A, B;
    reg Cin;
    wire [3:0] Sum;
    wire Cout;

    integer i, j, k;
    reg [4:0] expected_sum;

    parallel_adder_4bit dut (
        .A(A),
        .B(B),
        .Cin(Cin),
        .Sum(Sum),
        .Cout(Cout)
    );

    initial begin
        $dumpfile("tb_parallel_adder_4bit.vcd");
        $dumpvars(0, tb_parallel_adder_4bit);
        $display("Starting 4-bit Parallel Adder Testbench...");
        $display("A   B   Cin | Sum Cout | Expected | Pass/Fail");

        for (i = 0; i < 16; i = i + 1) begin
            for (j = 0; j < 16; j = j + 1) begin
                for (k = 0; k < 2; k = k + 1) begin
                    A = i[3:0];
                    B = j[3:0];
                    Cin = k[0];
                    #1;
                    expected_sum = A + B + Cin;

                    if ({Cout, Sum} == expected_sum) begin
                        $display("%b %b   %b   | %b   %b   | %b       | PASS",
                                 A, B, Cin, Sum, Cout, expected_sum);
                    end else begin
                        $display("%b %b   %b   | %b   %b   | %b       | FAIL <<<",
                                 A, B, Cin, Sum, Cout, expected_sum);
                    end
                end
            end
        end

        $finish;
    end

endmodule

tb_parallel_adder_4bit.vcd
$date
	Sun Jul 13 10:00:16 2025
$end
$version
	Icarus Verilog
$end
$timescale
	1s
$end
$scope module tb_parallel_adder_4bit $end
$var wire 4 ! Sum [3:0] $end
$var wire 1 " Cout $end
$var reg 4 # A [3:0] $end
$var reg 4 $ B [3:0] $end
$var reg 1 % Cin $end
$var reg 5 & expected_sum [4:0] $end
$var integer 32 ' i [31:0] $end
$var integer 32 ( j [31:0] $end
$var integer 32 ) k [31:0] $end
$scope module dut $end
$var wire 4 * A [3:0] $end
$var wire 4 + B [3:0] $end
$var wire 1 % Cin $end
$var wire 1 , c3 $end
$var wire 1 - c2 $end
$var wire 1 . c1 $end
$var wire 4 / Sum [3:0] $end
$var wire 1 " Cout $end
$scope module fa0 $end
$var wire 1 0 A $end
$var wire 1 1 B $end
$var wire 1 % Cin $end
$var wire 1 . Cout $end
$var wire 1 2 Sum $end
$upscope $end
$scope module fa1 $end
$var wire 1 3 A $end
$var wire 1 4 B $end
$var wire 1 . Cin $end
$var wire 1 - Cout $end
$var wire 1 5 Sum $end
$upscope $end
$scope module fa2 $end
$var wire 1 6 A $end
$var wire 1 7 B $end
$var wire 1 - Cin $end
$var wire 1 , Cout $end
$var wire 1 8 Sum $end
$upscope $end
$scope module fa3 $end
$var wire 1 9 A $end
$var wire 1 : B $end
$var wire 1 , Cin $end
$var wire 1 " Cout $end
$var wire 1 ; Sum $end
$upscope $end
$upscope $end
$upscope $end
$enddefinitions $end
$comment Show the parameter values. $end
$dumpall
$end
#0
$dumpvars
0;
0:
09
08
07
06
05
04
03
02
01
00
b0 /
0.
0-
0,
b0 +
b0 *
b0 )
b0 (
b0 '
bx &
0%
b0 $
b0 #
0"
b0 !
$end
#1
b1 !
b1 /
12
1%
b1 )
b0 &
#2
b1 !
b1 /
12
11
0%
b1 $
b1 +
b1 (
b0 )
b1 &
#3
15
1.
b10 !
b10 /
02
1%
b1 )
#4
08
0-
0.
15
b10 !
b10 /
02
01
14
0%
b10 $
b10 +
b10 (
b0 )
b10 &
#5
b11 !
b11 /
12
1%
b1 )
#6
b11 !
b11 /
12
11
0%
b11 $
b11 +
b11 (
b0 )
b11 &
#7
18
1-
05
1.
b100 !
b100 /
02
1%
b1 )
#8
0;
0-
0,
0.
05
18
b100 !
b100 /
02
01
04
17
0%
b100 $
b100 +
b100 (
b0 )
b100 &
#9
b101 !
b101 /
12
1%
b1 )
#10
b101 !
b101 /
12
11
0%
b101 $
b101 +
b101 (
b0 )
b101 &
#11
15
1.
b110 !
b110 /
02
1%
b1 )
#12
0;
0,
18
0-
0.
15
b110 !
b110 /
02
01
14
0%
b110 $
b110 +
b110 (
b0 )
b110 &
#13
b111 !
b111 /
12
1%
b1 )
#14
b111 !
b111 /
12
11
0%
b111 $
b111 +
b111 (
b0 )
b111 &
#15
1;
1,
08
1-
05
1.
b1000 !
b1000 /
02
1%
b1 )
#16
0-
0,
0"
0.
05
08
1;
b1000 !
b1000 /
02
01
04
07
1:
0%
b1000 $
b1000 +
b1000 (
b0 )
b1000 &
#17
b1001 !
b1001 /
12
1%
b1 )
#18
b1001 !
b1001 /
12
11
0%
b1001 $
b1001 +
b1001 (
b0 )
b1001 &
#19
15
1.
b1010 !
b1010 /
02
1%
b1 )
#20
08
0-
0.
15
b1010 !
b1010 /
02
01
14
0%
b1010 $
b1010 +
b1010 (
b0 )
b1010 &
#21
b1011 !
b1011 /
12
1%
b1 )
#22
b1011 !
b1011 /
12
11
0%
b1011 $
b1011 +
b1011 (
b0 )
b1011 &
#23
18
1-
05
1.
b1100 !
b1100 /
02
1%
b1 )
#24
0"
1;
0-
0,
0.
05
18
b1100 !
b1100 /
02
01
04
17
0%
b1100 $
b1100 +
b1100 (
b0 )
b1100 &
#25
b1101 !
b1101 /
12
1%
b1 )
#26
b1101 !
b1101 /
12
11
0%
b1101 $
b1101 +
b1101 (
b0 )
b1101 &
#27
15
1.
b1110 !
b1110 /
02
1%
b1 )
#28
0"
1;
0,
18
0-
0.
15
b1110 !
b1110 /
02
01
14
0%
b1110 $
b1110 +
b1110 (
b0 )
b1110 &
#29
b1111 !
b1111 /
12
1%
b1 )
#30
b1111 !
b1111 /
12
11
0%
b1111 $
b1111 +
b1111 (
b0 )
b1111 &
#31
1"
0;
1,
08
1-
05
1.
b0 !
b0 /
02
1%
b1 )
#32
0-
0,
0"
0.
05
08
0;
b1 !
b1 /
12
01
04
07
0:
10
0%
b0 $
b0 +
b1 #
b1 *
b1 '
b0 (
b0 )
b10000 &
#33
15
1.
b10 !
b10 /
02
1%
b1 )
b1 &
#34
15
1.
b10 !
b10 /
02
11
0%
b1 $
b1 +
b1 (
b0 )
b10 &
#35
b11 !
b11 /
12
1%
b1 )
#36
08
0-
0.
15
b11 !
b11 /
12
01
14
0%
b10 $
b10 +
b10 (
b0 )
b11 &
#37
18
1-
05
1.
b100 !
b100 /
02
1%
b1 )
#38
18
1-
05
1.
b100 !
b100 /
02
11
0%
b11 $
b11 +
b11 (
b0 )
b100 &
#39
b101 !
b101 /
12
1%
b1 )
#40
0;
0-
0,
0.
05
18
b101 !
b101 /
12
01
04
17
0%
b100 $
b100 +
b100 (
b0 )
b101 &
#41
15
1.
b110 !
b110 /
02
1%
b1 )
#42
15
1.
b110 !
b110 /
02
11
0%
b101 $
b101 +
b101 (
b0 )
b110 &
#43
b111 !
b111 /
12
1%
b1 )
#44
0;
0,
18
0-
0.
15
b111 !
b111 /
12
01
14
0%
b110 $
b110 +
b110 (
b0 )
b111 &
#45
1;
1,
08
1-
05
1.
b1000 !
b1000 /
02
1%
b1 )
#46
1;
1,
08
1-
05
1.
b1000 !
b1000 /
02
11
0%
b111 $
b111 +
b111 (
b0 )
b1000 &
#47
b1001 !
b1001 /
12
1%
b1 )
#48
0-
0,
0"
0.
05
08
1;
b1001 !
b1001 /
12
01
04
07
1:
0%
b1000 $
b1000 +
b1000 (
b0 )
b1001 &
#49
15
1.
b1010 !
b1010 /
02
1%
b1 )
#50
15
1.
b1010 !
b1010 /
02
11
0%
b1001 $
b1001 +
b1001 (
b0 )
b1010 &
#51
b1011 !
b1011 /
12
1%
b1 )
#52
08
0-
0.
15
b1011 !
b1011 /
12
01
14
0%
b1010 $
b1010 +
b1010 (
b0 )
b1011 &
#53
18
1-
05
1.
b1100 !
b1100 /
02
1%
b1 )
#54
18
1-
05
1.
b1100 !
b1100 /
02
11
0%
b1011 $
b1011 +
b1011 (
b0 )
b1100 &
#55
b1101 !
b1101 /
12
1%
b1 )
#56
0"
1;
0-
0,
0.
05
18
b1101 !
b1101 /
12
01
04
17
0%
b1100 $
b1100 +
b1100 (
b0 )
b1101 &
#57
15
1.
b1110 !
b1110 /
02
1%
b1 )
#58
15
1.
b1110 !
b1110 /
02
11
0%
b1101 $
b1101 +
b1101 (
b0 )
b1110 &
#59
b1111 !
b1111 /
12
1%
b1 )
#60
0"
1;
0,
18
0-
0.
15
b1111 !
b1111 /
12
01
14
0%
b1110 $
b1110 +
b1110 (
b0 )
b1111 &
#61
1"
0;
1,
08
1-
05
1.
b0 !
b0 /
02
1%
b1 )
#62
1"
0;
1,
08
1-
05
1.
b0 !
b0 /
02
11
0%
b1111 $
b1111 +
b1111 (
b0 )
b10000 &
#63
b1 !
b1 /
12
1%
b1 )
#64
0-
15
0,
0"
0.
08
0;
b10 !
b10 /
02
01
04
07
0:
00
13
0%
b0 $
b0 +
b10 #
b10 *
b10 '
b0 (
b0 )
b10001 &
#65
b11 !
b11 /
12
1%
b1 )
b10 &
#66
b11 !
b11 /
12
11
0%
b1 $
b1 +
b1 (
b0 )
b11 &
#67
18
1-
05
1.
b100 !
b100 /
02
1%
b1 )
#68
0.
05
b100 !
b100 /
02
01
14
0%
b10 $
b10 +
b10 (
b0 )
b100 &
#69
b101 !
b101 /
12
1%
b1 )
#70
b101 !
b101 /
12
11
0%
b11 $
b11 +
b11 (
b0 )
b101 &
#71
15
1.
b110 !
b110 /
02
1%
b1 )
#72
0-
0;
0,
0.
15
18
b110 !
b110 /
02
01
04
17
0%
b100 $
b100 +
b100 (
b0 )
b110 &
#73
b111 !
b111 /
12
1%
b1 )
#74
b111 !
b111 /
12
11
0%
b101 $
b101 +
b101 (
b0 )
b111 &
#75
1;
1,
08
1-
05
1.
b1000 !
b1000 /
02
1%
b1 )
#76
0.
05
b1000 !
b1000 /
02
01
14
0%
b110 $
b110 +
b110 (
b0 )
b1000 &
#77
b1001 !
b1001 /
12
1%
b1 )
#78
b1001 !
b1001 /
12
11
0%
b111 $
b111 +
b111 (
b0 )
b1001 &
#79
15
1.
b1010 !
b1010 /
02
1%
b1 )
#80
0-
0,
0"
0.
15
08
1;
b1010 !
b1010 /
02
01
04
07
1:
0%
b1000 $
b1000 +
b1000 (
b0 )
b1010 &
#81
b1011 !
b1011 /
12
1%
b1 )
#82
b1011 !
b1011 /
12
11
0%
b1001 $
b1001 +
b1001 (
b0 )
b1011 &
#83
18
1-
05
1.
b1100 !
b1100 /
02
1%
b1 )
#84
0.
05
b1100 !
b1100 /
02
01
14
0%
b1010 $
b1010 +
b1010 (
b0 )
b1100 &
#85
b1101 !
b1101 /
12
1%
b1 )
#86
b1101 !
b1101 /
12
11
0%
b1011 $
b1011 +
b1011 (
b0 )
b1101 &
#87
15
1.
b1110 !
b1110 /
02
1%
b1 )
#88
0"
0-
1;
0,
0.
15
18
b1110 !
b1110 /
02
01
04
17
0%
b1100 $
b1100 +
b1100 (
b0 )
b1110 &
#89
b1111 !
b1111 /
12
1%
b1 )
#90
b1111 !
b1111 /
12
11
0%
b1101 $
b1101 +
b1101 (
b0 )
b1111 &
#91
1"
0;
1,
08
1-
05
1.
b0 !
b0 /
02
1%
b1 )
#92
0.
05
b0 !
b0 /
02
01
14
0%
b1110 $
b1110 +
b1110 (
b0 )
b10000 &
#93
b1 !
b1 /
12
1%
b1 )
#94
b1 !
b1 /
12
11
0%
b1111 $
b1111 +
b1111 (
b0 )
b10001 &
#95
15
1.
b10 !
b10 /
02
1%
b1 )
#96
0-
0,
0"
0.
15
08
0;
b11 !
b11 /
12
01
04
07
0:
10
0%
b0 $
b0 +
b11 #
b11 *
b11 '
b0 (
b0 )
b10010 &
#97
18
1-
05
1.
b100 !
b100 /
02
1%
b1 )
b11 &
#98
18
1-
05
1.
b100 !
b100 /
02
11
0%
b1 $
b1 +
b1 (
b0 )
b100 &
#99
b101 !
b101 /
12
1%
b1 )
#100
0.
05
b101 !
b101 /
12
01
14
0%
b10 $
b10 +
b10 (
b0 )
b101 &
#101
15
1.
b110 !
b110 /
02
1%
b1 )
#102
15
1.
b110 !
b110 /
02
11
0%
b11 $
b11 +
b11 (
b0 )
b110 &
#103
b111 !
b111 /
12
1%
b1 )
#104
0-
0;
0,
0.
15
18
b111 !
b111 /
12
01
04
17
0%
b100 $
b100 +
b100 (
b0 )
b111 &
#105
1;
1,
08
1-
05
1.
b1000 !
b1000 /
02
1%
b1 )
#106
1;
1,
08
1-
05
1.
b1000 !
b1000 /
02
11
0%
b101 $
b101 +
b101 (
b0 )
b1000 &
#107
b1001 !
b1001 /
12
1%
b1 )
#108
0.
05
b1001 !
b1001 /
12
01
14
0%
b110 $
b110 +
b110 (
b0 )
b1001 &
#109
15
1.
b1010 !
b1010 /
02
1%
b1 )
#110
15
1.
b1010 !
b1010 /
02
11
0%
b111 $
b111 +
b111 (
b0 )
b1010 &
#111
b1011 !
b1011 /
12
1%
b1 )
#112
0-
0,
0"
0.
15
08
1;
b1011 !
b1011 /
12
01
04
07
1:
0%
b1000 $
b1000 +
b1000 (
b0 )
b1011 &
#113
18
1-
05
1.
b1100 !
b1100 /
02
1%
b1 )
#114
18
1-
05
1.
b1100 !
b1100 /
02
11
0%
b1001 $
b1001 +
b1001 (
b0 )
b1100 &
#115
b1101 !
b1101 /
12
1%
b1 )
#116
0.
05
b1101 !
b1101 /
12
01
14
0%
b1010 $
b1010 +
b1010 (
b0 )
b1101 &
#117
15
1.
b1110 !
b1110 /
02
1%
b1 )
#118
15
1.
b1110 !
b1110 /
02
11
0%
b1011 $
b1011 +
b1011 (
b0 )
b1110 &
#119
b1111 !
b1111 /
12
1%
b1 )
#120
0"
0-
1;
0,
0.
15
18
b1111 !
b1111 /
12
01
04
17
0%
b1100 $
b1100 +
b1100 (
b0 )
b1111 &
#121
1"
0;
1,
08
1-
05
1.
b0 !
b0 /
02
1%
b1 )
#122
1"
0;
1,
08
1-
05
1.
b0 !
b0 /
02
11
0%
b1101 $
b1101 +
b1101 (
b0 )
b10000 &
#123
b1 !
b1 /
12
1%
b1 )
#124
0.
05
b1 !
b1 /
12
01
14
0%
b1110 $
b1110 +
b1110 (
b0 )
b10001 &
#125
15
1.
b10 !
b10 /
02
1%
b1 )
#126
15
1.
b10 !
b10 /
02
11
0%
b1111 $
b1111 +
b1111 (
b0 )
b10010 &
#127
b11 !
b11 /
12
1%
b1 )
#128
0,
18
05
0"
0-
0.
0;
b100 !
b100 /
02
01
04
07
0:
00
03
16
0%
b0 $
b0 +
b100 #
b100 *
b100 '
b0 (
b0 )
b10011 &
#129
b101 !
b101 /
12
1%
b1 )
b100 &
#130
b101 !
b101 /
12
11
0%
b1 $
b1 +
b1 (
b0 )
b101 &
#131
15
1.
b110 !
b110 /
02
1%
b1 )
#132
0;
0,
18
0-
0.
15
b110 !
b110 /
02
01
14
0%
b10 $
b10 +
b10 (
b0 )
b110 &
#133
b111 !
b111 /
12
1%
b1 )
#134
b111 !
b111 /
12
11
0%
b11 $
b11 +
b11 (
b0 )
b111 &
#135
1;
1,
08
1-
05
1.
b1000 !
b1000 /
02
1%
b1 )
#136
0-
0.
05
08
b1000 !
b1000 /
02
01
04
17
0%
b100 $
b100 +
b100 (
b0 )
b1000 &
#137
b1001 !
b1001 /
12
1%
b1 )
#138
b1001 !
b1001 /
12
11
0%
b101 $
b101 +
b101 (
b0 )
b1001 &
#139
15
1.
b1010 !
b1010 /
02
1%
b1 )
#140
08
0-
0.
15
b1010 !
b1010 /
02
01
14
0%
b110 $
b110 +
b110 (
b0 )
b1010 &
#141
b1011 !
b1011 /
12
1%
b1 )
#142
b1011 !
b1011 /
12
11
0%
b111 $
b111 +
b111 (
b0 )
b1011 &
#143
18
1-
05
1.
b1100 !
b1100 /
02
1%
b1 )
#144
0,
0-
0"
0.
05
18
1;
b1100 !
b1100 /
02
01
04
07
1:
0%
b1000 $
b1000 +
b1000 (
b0 )
b1100 &
#145
b1101 !
b1101 /
12
1%
b1 )
#146
b1101 !
b1101 /
12
11
0%
b1001 $
b1001 +
b1001 (
b0 )
b1101 &
#147
15
1.
b1110 !
b1110 /
02
1%
b1 )
#148
0"
1;
0,
18
0-
0.
15
b1110 !
b1110 /
02
01
14
0%
b1010 $
b1010 +
b1010 (
b0 )
b1110 &
#149
b1111 !
b1111 /
12
1%
b1 )
#150
b1111 !
b1111 /
12
11
0%
b1011 $
b1011 +
b1011 (
b0 )
b1111 &
#151
1"
0;
1,
08
1-
05
1.
b0 !
b0 /
02
1%
b1 )
#152
0-
0.
05
08
b0 !
b0 /
02
01
04
17
0%
b1100 $
b1100 +
b1100 (
b0 )
b10000 &
#153
b1 !
b1 /
12
1%
b1 )
#154
b1 !
b1 /
12
11
0%
b1101 $
b1101 +
b1101 (
b0 )
b10001 &
#155
15
1.
b10 !
b10 /
02
1%
b1 )
#156
08
0-
0.
15
b10 !
b10 /
02
01
14
0%
b1110 $
b1110 +
b1110 (
b0 )
b10010 &
#157
b11 !
b11 /
12
1%
b1 )
#158
b11 !
b11 /
12
11
0%
b1111 $
b1111 +
b1111 (
b0 )
b10011 &
#159
18
1-
05
1.
b100 !
b100 /
02
1%
b1 )
#160
0,
0-
0"
0.
05
18
0;
b101 !
b101 /
12
01
04
07
0:
10
0%
b0 $
b0 +
b101 #
b101 *
b101 '
b0 (
b0 )
b10100 &
#161
15
1.
b110 !
b110 /
02
1%
b1 )
b101 &
#162
15
1.
b110 !
b110 /
02
11
0%
b1 $
b1 +
b1 (
b0 )
b110 &
#163
b111 !
b111 /
12
1%
b1 )
#164
0;
0,
18
0-
0.
15
b111 !
b111 /
12
01
14
0%
b10 $
b10 +
b10 (
b0 )
b111 &
#165
1;
1,
08
1-
05
1.
b1000 !
b1000 /
02
1%
b1 )
#166
1;
1,
08
1-
05
1.
b1000 !
b1000 /
02
11
0%
b11 $
b11 +
b11 (
b0 )
b1000 &
#167
b1001 !
b1001 /
12
1%
b1 )
#168
0-
0.
05
08
b1001 !
b1001 /
12
01
04
17
0%
b100 $
b100 +
b100 (
b0 )
b1001 &
#169
15
1.
b1010 !
b1010 /
02
1%
b1 )
#170
15
1.
b1010 !
b1010 /
02
11
0%
b101 $
b101 +
b101 (
b0 )
b1010 &
#171
b1011 !
b1011 /
12
1%
b1 )
#172
08
0-
0.
15
b1011 !
b1011 /
12
01
14
0%
b110 $
b110 +
b110 (
b0 )
b1011 &
#173
18
1-
05
1.
b1100 !
b1100 /
02
1%
b1 )
#174
18
1-
05
1.
b1100 !
b1100 /
02
11
0%
b111 $
b111 +
b111 (
b0 )
b1100 &
#175
b1101 !
b1101 /
12
1%
b1 )
#176
0,
0-
0"
0.
05
18
1;
b1101 !
b1101 /
12
01
04
07
1:
0%
b1000 $
b1000 +
b1000 (
b0 )
b1101 &
#177
15
1.
b1110 !
b1110 /
02
1%
b1 )
#178
15
1.
b1110 !
b1110 /
02
11
0%
b1001 $
b1001 +
b1001 (
b0 )
b1110 &
#179
b1111 !
b1111 /
12
1%
b1 )
#180
0"
1;
0,
18
0-
0.
15
b1111 !
b1111 /
12
01
14
0%
b1010 $
b1010 +
b1010 (
b0 )
b1111 &
#181
1"
0;
1,
08
1-
05
1.
b0 !
b0 /
02
1%
b1 )
#182
1"
0;
1,
08
1-
05
1.
b0 !
b0 /
02
11
0%
b1011 $
b1011 +
b1011 (
b0 )
b10000 &
#183
b1 !
b1 /
12
1%
b1 )
#184
0-
0.
05
08
b1 !
b1 /
12
01
04
17
0%
b1100 $
b1100 +
b1100 (
b0 )
b10001 &
#185
15
1.
b10 !
b10 /
02
1%
b1 )
#186
15
1.
b10 !
b10 /
02
11
0%
b1101 $
b1101 +
b1101 (
b0 )
b10010 &
#187
b11 !
b11 /
12
1%
b1 )
#188
08
0-
0.
15
b11 !
b11 /
12
01
14
0%
b1110 $
b1110 +
b1110 (
b0 )
b10011 &
#189
18
1-
05
1.
b100 !
b100 /
02
1%
b1 )
#190
18
1-
05
1.
b100 !
b100 /
02
11
0%
b1111 $
b1111 +
b1111 (
b0 )
b10100 &
#191
b101 !
b101 /
12
1%
b1 )
#192
0,
0-
15
0"
0.
18
0;
b110 !
b110 /
02
01
04
07
0:
00
13
0%
b0 $
b0 +
b110 #
b110 *
b110 '
b0 (
b0 )
b10101 &
#193
b111 !
b111 /
12
1%
b1 )
b110 &
#194
b111 !
b111 /
12
11
0%
b1 $
b1 +
b1 (
b0 )
b111 &
#195
1;
1,
08
1-
05
1.
b1000 !
b1000 /
02
1%
b1 )
#196
0.
05
b1000 !
b1000 /
02
01
14
0%
b10 $
b10 +
b10 (
b0 )
b1000 &
#197
b1001 !
b1001 /
12
1%
b1 )
#198
b1001 !
b1001 /
12
11
0%
b11 $
b11 +
b11 (
b0 )
b1001 &
#199
15
1.
b1010 !
b1010 /
02
1%
b1 )
#200
0-
0.
15
08
b1010 !
b1010 /
02
01
04
17
0%
b100 $
b100 +
b100 (
b0 )
b1010 &
#201
b1011 !
b1011 /
12
1%
b1 )
#202
b1011 !
b1011 /
12
11
0%
b101 $
b101 +
b101 (
b0 )
b1011 &
#203
18
1-
05
1.
b1100 !
b1100 /
02
1%
b1 )
#204
0.
05
b1100 !
b1100 /
02
01
14
0%
b110 $
b110 +
b110 (
b0 )
b1100 &
#205
b1101 !
b1101 /
12
1%
b1 )
#206
b1101 !
b1101 /
12
11
0%
b111 $
b111 +
b111 (
b0 )
b1101 &
#207
15
1.
b1110 !
b1110 /
02
1%
b1 )
#208
0,
0-
0"
0.
15
18
1;
b1110 !
b1110 /
02
01
04
07
1:
0%
b1000 $
b1000 +
b1000 (
b0 )
b1110 &
#209
b1111 !
b1111 /
12
1%
b1 )
#210
b1111 !
b1111 /
12
11
0%
b1001 $
b1001 +
b1001 (
b0 )
b1111 &
#211
1"
0;
1,
08
1-
05
1.
b0 !
b0 /
02
1%
b1 )
#212
0.
05
b0 !
b0 /
02
01
14
0%
b1010 $
b1010 +
b1010 (
b0 )
b10000 &
#213
b1 !
b1 /
12
1%
b1 )
#214
b1 !
b1 /
12
11
0%
b1011 $
b1011 +
b1011 (
b0 )
b10001 &
#215
15
1.
b10 !
b10 /
02
1%
b1 )
#216
0-
0.
15
08
b10 !
b10 /
02
01
04
17
0%
b1100 $
b1100 +
b1100 (
b0 )
b10010 &
#217
b11 !
b11 /
12
1%
b1 )
#218
b11 !
b11 /
12
11
0%
b1101 $
b1101 +
b1101 (
b0 )
b10011 &
#219
18
1-
05
1.
b100 !
b100 /
02
1%
b1 )
#220
0.
05
b100 !
b100 /
02
01
14
0%
b1110 $
b1110 +
b1110 (
b0 )
b10100 &
#221
b101 !
b101 /
12
1%
b1 )
#222
b101 !
b101 /
12
11
0%
b1111 $
b1111 +
b1111 (
b0 )
b10101 &
#223
15
1.
b110 !
b110 /
02
1%
b1 )
#224
0,
0-
0"
0.
15
18
0;
b111 !
b111 /
12
01
04
07
0:
10
0%
b0 $
b0 +
b111 #
b111 *
b111 '
b0 (
b0 )
b10110 &
#225
1;
1,
08
1-
05
1.
b1000 !
b1000 /
02
1%
b1 )
b111 &
#226
1;
1,
08
1-
05
1.
b1000 !
b1000 /
02
11
0%
b1 $
b1 +
b1 (
b0 )
b1000 &
#227
b1001 !
b1001 /
12
1%
b1 )
#228
0.
05
b1001 !
b1001 /
12
01
14
0%
b10 $
b10 +
b10 (
b0 )
b1001 &
#229
15
1.
b1010 !
b1010 /
02
1%
b1 )
#230
15
1.
b1010 !
b1010 /
02
11
0%
b11 $
b11 +
b11 (
b0 )
b1010 &
#231
b1011 !
b1011 /
12
1%
b1 )
#232
0-
0.
15
08
b1011 !
b1011 /
12
01
04
17
0%
b100 $
b100 +
b100 (
b0 )
b1011 &
#233
18
1-
05
1.
b1100 !
b1100 /
02
1%
b1 )
#234
18
1-
05
1.
b1100 !
b1100 /
02
11
0%
b101 $
b101 +
b101 (
b0 )
b1100 &
#235
b1101 !
b1101 /
12
1%
b1 )
#236
0.
05
b1101 !
b1101 /
12
01
14
0%
b110 $
b110 +
b110 (
b0 )
b1101 &
#237
15
1.
b1110 !
b1110 /
02
1%
b1 )
#238
15
1.
b1110 !
b1110 /
02
11
0%
b111 $
b111 +
b111 (
b0 )
b1110 &
#239
b1111 !
b1111 /
12
1%
b1 )
#240
0,
0-
0"
0.
15
18
1;
b1111 !
b1111 /
12
01
04
07
1:
0%
b1000 $
b1000 +
b1000 (
b0 )
b1111 &
#241
1"
0;
1,
08
1-
05
1.
b0 !
b0 /
02
1%
b1 )
#242
1"
0;
1,
08
1-
05
1.
b0 !
b0 /
02
11
0%
b1001 $
b1001 +
b1001 (
b0 )
b10000 &
#243
b1 !
b1 /
12
1%
b1 )
#244
0.
05
b1 !
b1 /
12
01
14
0%
b1010 $
b1010 +
b1010 (
b0 )
b10001 &
#245
15
1.
b10 !
b10 /
02
1%
b1 )
#246
15
1.
b10 !
b10 /
02
11
0%
b1011 $
b1011 +
b1011 (
b0 )
b10010 &
#247
b11 !
b11 /
12
1%
b1 )
#248
0-
0.
15
08
b11 !
b11 /
12
01
04
17
0%
b1100 $
b1100 +
b1100 (
b0 )
b10011 &
#249
18
1-
05
1.
b100 !
b100 /
02
1%
b1 )
#250
18
1-
05
1.
b100 !
b100 /
02
11
0%
b1101 $
b1101 +
b1101 (
b0 )
b10100 &
#251
b101 !
b101 /
12
1%
b1 )
#252
0.
05
b101 !
b101 /
12
01
14
0%
b1110 $
b1110 +
b1110 (
b0 )
b10101 &
#253
15
1.
b110 !
b110 /
02
1%
b1 )
#254
15
1.
b110 !
b110 /
02
11
0%
b1111 $
b1111 +
b1111 (
b0 )
b10110 &
#255
b111 !
b111 /
12
1%
b1 )
#256
0"
08
1;
05
0-
0,
0.
b1000 !
b1000 /
02
01
04
07
0:
00
03
06
19
0%
b0 $
b0 +
b1000 #
b1000 *
b1000 '
b0 (
b0 )
b10111 &
#257
b1001 !
b1001 /
12
1%
b1 )
b1000 &
#258
b1001 !
b1001 /
12
11
0%
b1 $
b1 +
b1 (
b0 )
b1001 &
#259
15
1.
b1010 !
b1010 /
02
1%
b1 )
#260
08
0-
0.
15
b1010 !
b1010 /
02
01
14
0%
b10 $
b10 +
b10 (
b0 )
b1010 &
#261
b1011 !
b1011 /
12
1%
b1 )
#262
b1011 !
b1011 /
12
11
0%
b11 $
b11 +
b11 (
b0 )
b1011 &
#263
18
1-
05
1.
b1100 !
b1100 /
02
1%
b1 )
#264
0"
1;
0-
0,
0.
05
18
b1100 !
b1100 /
02
01
04
17
0%
b100 $
b100 +
b100 (
b0 )
b1100 &
#265
b1101 !
b1101 /
12
1%
b1 )
#266
b1101 !
b1101 /
12
11
0%
b101 $
b101 +
b101 (
b0 )
b1101 &
#267
15
1.
b1110 !
b1110 /
02
1%
b1 )
#268
0"
1;
0,
18
0-
0.
15
b1110 !
b1110 /
02
01
14
0%
b110 $
b110 +
b110 (
b0 )
b1110 &
#269
b1111 !
b1111 /
12
1%
b1 )
#270
b1111 !
b1111 /
12
11
0%
b111 $
b111 +
b111 (
b0 )
b1111 &
#271
1"
0;
1,
08
1-
05
1.
b0 !
b0 /
02
1%
b1 )
#272
0-
0,
0.
05
08
0;
b0 !
b0 /
02
01
04
07
1:
0%
b1000 $
b1000 +
b1000 (
b0 )
b10000 &
#273
b1 !
b1 /
12
1%
b1 )
#274
b1 !
b1 /
12
11
0%
b1001 $
b1001 +
b1001 (
b0 )
b10001 &
#275
15
1.
b10 !
b10 /
02
1%
b1 )
#276
08
0-
0.
15
b10 !
b10 /
02
01
14
0%
b1010 $
b1010 +
b1010 (
b0 )
b10010 &
#277
b11 !
b11 /
12
1%
b1 )
#278
b11 !
b11 /
12
11
0%
b1011 $
b1011 +
b1011 (
b0 )
b10011 &
#279
18
1-
05
1.
b100 !
b100 /
02
1%
b1 )
#280
0;
0-
0,
0.
05
18
b100 !
b100 /
02
01
04
17
0%
b1100 $
b1100 +
b1100 (
b0 )
b10100 &
#281
b101 !
b101 /
12
1%
b1 )
#282
b101 !
b101 /
12
11
0%
b1101 $
b1101 +
b1101 (
b0 )
b10101 &
#283
15
1.
b110 !
b110 /
02
1%
b1 )
#284
0;
0,
18
0-
0.
15
b110 !
b110 /
02
01
14
0%
b1110 $
b1110 +
b1110 (
b0 )
b10110 &
#285
b111 !
b111 /
12
1%
b1 )
#286
b111 !
b111 /
12
11
0%
b1111 $
b1111 +
b1111 (
b0 )
b10111 &
#287
1;
1,
08
1-
05
1.
b1000 !
b1000 /
02
1%
b1 )
#288
0"
0-
0,
0.
05
08
1;
b1001 !
b1001 /
12
01
04
07
0:
10
0%
b0 $
b0 +
b1001 #
b1001 *
b1001 '
b0 (
b0 )
b11000 &
#289
15
1.
b1010 !
b1010 /
02
1%
b1 )
b1001 &
#290
15
1.
b1010 !
b1010 /
02
11
0%
b1 $
b1 +
b1 (
b0 )
b1010 &
#291
b1011 !
b1011 /
12
1%
b1 )
#292
08
0-
0.
15
b1011 !
b1011 /
12
01
14
0%
b10 $
b10 +
b10 (
b0 )
b1011 &
#293
18
1-
05
1.
b1100 !
b1100 /
02
1%
b1 )
#294
18
1-
05
1.
b1100 !
b1100 /
02
11
0%
b11 $
b11 +
b11 (
b0 )
b1100 &
#295
b1101 !
b1101 /
12
1%
b1 )
